{
  "type": "standard",
  "id": "deer_red",
  "path": "animals/deer",
  "animations": {
    "walk": {
      "type": "simple",
      "key": "walk",
      "file": "animals/deer/deer_red_animation1.png",
      "category": "movement",
      "loops": true,
      "frames": {
        "sheetWidth": 0,
        "sheetHeight": 0,
        "frameWidth": 0,
        "frameHeight": 0,
        "frameCount": 0
      },
      "originalName": "deer_red_animation1"
    },
    "idle": {
      "type": "simple",
      "key": "idle",
      "file": "animals/deer/deer_red_animation2.png",
      "category": "movement",
      "loops": true,
      "frames": {
        "sheetWidth": 0,
        "sheetHeight": 0,
        "frameWidth": 0,
        "frameHeight": 0,
        "frameCount": 0
      },
      "originalName": "deer_red_animation2"
    },
    "look_up": {
      "type": "simple",
      "key": "look_up",
      "file": "animals/deer/deer_red_animation3.png",
      "category": "movement",
      "loops": true,
      "frames": {
        "sheetWidth": 0,
        "sheetHeight": 0,
        "frameWidth": 0,
        "frameHeight": 0,
        "frameCount": 0
      },
      "originalName": "deer_red_animation3"
    },
    "death": {
      "type": "simple",
      "key": "death",
      "file": "animals/deer/deer_red_animation4.png",
      "category": "movement",
      "loops": true,
      "frames": {
        "sheetWidth": 0,
        "sheetHeight": 0,
        "frameWidth": 0,
        "frameHeight": 0,
        "frameCount": 0
      },
      "originalName": "deer_red_animation4"
    }
  }
}