{
  "biome": "castle_of_bones",
  "path": "castle_of_bones/objects/animated_objects",
  "objects": {
    "ancient_door": {
      "type": "standard",
      "id": "ancient_door",
      "path": "castle_of_bones/objects/animated_objects/ancient_door",
      "animations": {
        "idle": {
          "type": "simple",
          "key": "idle",
          "file": "castle_of_bones/objects/animated_objects/ancient_door/idle.png",
          "category": "movement",
          "loops": true,
          "frames": {
            "sheetWidth": 64,
            "sheetHeight": 144,
            "frameWidth": 64,
            "frameHeight": 144,
            "frameCount": 1
          },
          "originalName": "idle"
        },
        "open": {
          "type": "simple",
          "key": "open",
          "file": "castle_of_bones/objects/animated_objects/ancient_door/open.png",
          "category": "movement",
          "loops": true,
          "frames": {
            "sheetWidth": 3072,
            "sheetHeight": 144,
            "frameWidth": 64,
            "frameHeight": 144,
            "frameCount": 48
          },
          "originalName": "open"
        }
      }
    },
    "ancient_door_idle": {
      "type": "standard",
      "id": "ancient_door_idle",
      "path": "castle_of_bones/objects/animated_objects",
      "animations": {
        "idle": {
          "type": "simple",
          "key": "idle",
          "file": "castle_of_bones/objects/animated_objects/ancient_door_idle.png",
          "category": "movement",
          "loops": true,
          "frames": {
            "sheetWidth": 100,
            "sheetHeight": 144,
            "frameWidth": 100,
            "frameHeight": 144,
            "frameCount": 1
          },
          "originalName": "ancient_door_idle"
        }
      }
    },
    "candles_animation1": {
      "type": "standard",
      "id": "candles_animation1",
      "path": "castle_of_bones/objects/animated_objects",
      "animations": {
        "idle": {
          "type": "simple",
          "key": "idle",
          "file": "castle_of_bones/objects/animated_objects/candles_animation1.png",
          "category": "movement",
          "loops": true,
          "frames": {
            "sheetWidth": 256,
            "sheetHeight": 18,
            "frameWidth": 32,
            "frameHeight": 18,
            "frameCount": 8
          },
          "originalName": "candles_animation1"
        }
      }
    },
    "candles_animation2": {
      "type": "standard",
      "id": "candles_animation2",
      "path": "castle_of_bones/objects/animated_objects",
      "animations": {
        "idle": {
          "type": "simple",
          "key": "idle",
          "file": "castle_of_bones/objects/animated_objects/candles_animation2.png",
          "category": "movement",
          "loops": true,
          "frames": {
            "sheetWidth": 256,
            "sheetHeight": 15,
            "frameWidth": 32,
            "frameHeight": 15,
            "frameCount": 8
          },
          "originalName": "candles_animation2"
        }
      }
    },
    "candles_animation3": {
      "type": "standard",
      "id": "candles_animation3",
      "path": "castle_of_bones/objects/animated_objects",
      "animations": {
        "idle": {
          "type": "simple",
          "key": "idle",
          "file": "castle_of_bones/objects/animated_objects/candles_animation3.png",
          "category": "movement",
          "loops": true,
          "frames": {
            "sheetWidth": 256,
            "sheetHeight": 18,
            "frameWidth": 32,
            "frameHeight": 18,
            "frameCount": 8
          },
          "originalName": "candles_animation3"
        }
      }
    },
    "ember_pit_shrine_idle": {
      "type": "standard",
      "id": "ember_pit_shrine_idle",
      "path": "castle_of_bones/objects/animated_objects",
      "animations": {
        "idle": {
          "type": "simple",
          "key": "idle",
          "file": "castle_of_bones/objects/animated_objects/ember_pit_shrine_idle.png",
          "category": "movement",
          "loops": true,
          "frames": {
            "sheetWidth": 320,
            "sheetHeight": 33,
            "frameWidth": 80,
            "frameHeight": 33,
            "frameCount": 4
          },
          "originalName": "ember_pit_shrine_idle"
        }
      }
    },
    "torch_1_idle": {
      "type": "standard",
      "id": "torch_1_idle",
      "path": "castle_of_bones/objects/animated_objects",
      "animations": {
        "idle": {
          "type": "simple",
          "key": "idle",
          "file": "castle_of_bones/objects/animated_objects/torch_1_idle.png",
          "category": "movement",
          "loops": true,
          "frames": {
            "sheetWidth": 640,
            "sheetHeight": 64,
            "frameWidth": 64,
            "frameHeight": 64,
            "frameCount": 10
          },
          "originalName": "torch_1_idle"
        }
      }
    }
  }
}