{
  "type": "standard",
  "id": "hell_bot_dark",
  "path": "characters/hell_bot_dark",
  "animations": {
    "attack1": {
      "type": "simple",
      "key": "attack1",
      "file": "characters/hell_bot_dark/attack.png",
      "category": "attack",
      "loops": false,
      "frames": {
        "sheetWidth": 552,
        "sheetHeight": 36,
        "frameWidth": 92,
        "frameHeight": 36,
        "frameCount": 6
      },
      "originalName": "attack"
    },
    "death": {
      "type": "simple",
      "key": "death",
      "file": "characters/hell_bot_dark/death.png",
      "category": "state",
      "loops": false,
      "frames": {
        "sheetWidth": 1012,
        "sheetHeight": 36,
        "frameWidth": 92,
        "frameHeight": 36,
        "frameCount": 11
      },
      "originalName": "death"
    },
    "take_hit": {
      "type": "simple",
      "key": "take_hit",
      "file": "characters/hell_bot_dark/hit.png",
      "category": "state",
      "loops": false,
      "frames": {
        "sheetWidth": 184,
        "sheetHeight": 36,
        "frameWidth": 92,
        "frameHeight": 36,
        "frameCount": 2
      },
      "originalName": "hit"
    },
    "idle": {
      "type": "simple",
      "key": "idle",
      "file": "characters/hell_bot_dark/idle.png",
      "category": "movement",
      "loops": true,
      "frames": {
        "sheetWidth": 552,
        "sheetHeight": 36,
        "frameWidth": 92,
        "frameHeight": 36,
        "frameCount": 6
      },
      "originalName": "idle"
    },
    "run": {
      "type": "simple",
      "key": "run",
      "file": "characters/hell_bot_dark/run.png",
      "category": "movement",
      "loops": true,
      "frames": {
        "sheetWidth": 736,
        "sheetHeight": 36,
        "frameWidth": 92,
        "frameHeight": 36,
        "frameCount": 8
      },
      "originalName": "run"
    },
    "attack2": {
      "type": "simple",
      "key": "attack2",
      "file": "characters/hell_bot_dark/shoot.png",
      "category": "ranged",
      "loops": false,
      "frames": {
        "sheetWidth": 552,
        "sheetHeight": 36,
        "frameWidth": 92,
        "frameHeight": 36,
        "frameCount": 6
      },
      "originalName": "shoot"
    }
  }
}